wintemp/wintemp.py
wintemp-1.0.0.dist-info/METADATA
wintemp-1.0.0.dist-info/WHEEL
wintemp-1.0.0.dist-info/top_level.txt
wintemp-1.0.0.dist-info/RECORD
