Metadata-Version: 2.1
Name: wintemp
Version: 1.0.0
Summary: Remove Windows Temporary Files
Home-page: UNKNOWN
Author: Arjun Basandrai
Author-email: arjunbasandrai2004@gmail.com
License: UNKNOWN
Platform: UNKNOWN
